df_fingerprint/__init__.py
df_fingerprint/_version.py
df_fingerprint/core.py
df_fingerprint/spec.py
dataframe_fingerprint-0.1.0.dist-info/METADATA
dataframe_fingerprint-0.1.0.dist-info/WHEEL
dataframe_fingerprint-0.1.0.dist-info/licenses/LICENSE
dataframe_fingerprint-0.1.0.dist-info/RECORD
