Metadata-Version: 2.4
Name: dataframe-fingerprint
Version: 0.1.0
Summary: Stable, cross-environment fingerprints for pandas DataFrames via canonicalization + hashing.
Project-URL: Homepage, https://github.com/hjk612/df-fingerprint
Project-URL: Issues, https://github.com/hjk612/df-fingerprint/issues
Author-email: Hatim Kagalwala <hatim.kagalwala@gmail.com>
License-Expression: MIT
License-File: LICENSE
Keywords: dataframe,fingerprint,hash,mlops,pandas,reproducibility
Classifier: Development Status :: 4 - Beta
Classifier: Intended Audience :: Developers
Classifier: Intended Audience :: Science/Research
Classifier: License :: OSI Approved :: MIT License
Classifier: Operating System :: OS Independent
Classifier: Programming Language :: Python :: 3
Classifier: Programming Language :: Python :: 3.9
Classifier: Programming Language :: Python :: 3.10
Classifier: Programming Language :: Python :: 3.11
Classifier: Programming Language :: Python :: 3.12
Classifier: Topic :: Database
Classifier: Topic :: Scientific/Engineering
Classifier: Topic :: Scientific/Engineering :: Information Analysis
Classifier: Topic :: Software Development :: Libraries :: Python Modules
Classifier: Topic :: Utilities
Requires-Python: >=3.9
Requires-Dist: numpy>=1.23
Requires-Dist: pandas>=1.5
Requires-Dist: python-dateutil>=2.8
Provides-Extra: dev
Requires-Dist: black; extra == 'dev'
Requires-Dist: hypothesis>=6.0; extra == 'dev'
Requires-Dist: isort; extra == 'dev'
Requires-Dist: mypy; extra == 'dev'
Requires-Dist: pytest>=7.0; extra == 'dev'
Provides-Extra: test
Requires-Dist: hypothesis>=6.0; extra == 'test'
Requires-Dist: pytest>=7.0; extra == 'test'
